sprocketship/cli.py
sprocketship/utils.py
sprocketship/templates/javascript.sql
sprocketship-1.1.1.dist-info/LICENSE
sprocketship-1.1.1.dist-info/METADATA
sprocketship-1.1.1.dist-info/WHEEL
sprocketship-1.1.1.dist-info/entry_points.txt
sprocketship-1.1.1.dist-info/top_level.txt
sprocketship-1.1.1.dist-info/RECORD
