Metadata-Version: 2.1
Name: sprocketship
Version: 1.1.1
Summary: Better stored procedure management
Author-email: Nicklaus Roach <nicklausroach@gmail.com>
Project-URL: Homepage, https://github.com/nicklausroach/sprocketship
Project-URL: Issues, https://github.com/nicklausroach/sprocketship/issues
Classifier: Programming Language :: Python :: 3
Classifier: License :: OSI Approved :: MIT License
Classifier: Operating System :: OS Independent
License-File: LICENSE
Requires-Dist: click
Requires-Dist: cryptography
Requires-Dist: snowflake-connector-python
Requires-Dist: ABSQL
Requires-Dist: ruamel.yaml
Requires-Dist: jinja2
